cdk_organizations_list_accounts/__init__.py
cdk_organizations_list_accounts/py.typed
cdk_organizations_list_accounts/_jsii/__init__.py
cdk_organizations_list_accounts/_jsii/cdk-organizations-list-accounts@1.0.328.jsii.tgz
cdk_organizations_list_accounts-1.0.328.dist-info/LICENSE
cdk_organizations_list_accounts-1.0.328.dist-info/METADATA
cdk_organizations_list_accounts-1.0.328.dist-info/WHEEL
cdk_organizations_list_accounts-1.0.328.dist-info/top_level.txt
cdk_organizations_list_accounts-1.0.328.dist-info/RECORD
