Metadata-Version: 2.1
Name: cdk-organizations-list-accounts
Version: 1.0.328
Summary: cdk-organizations-list-accounts is an AWS CDK building library that outputs a list of AWS organization accounts in CSV format.
Home-page: https://github.com/hayao-k/cdk-organizations-list-accounts.git
Author: hayao-k<30886141+hayao-k@users.noreply.github.com>
License: Apache-2.0
Project-URL: Source, https://github.com/hayao-k/cdk-organizations-list-accounts.git
Classifier: Intended Audience :: Developers
Classifier: Operating System :: OS Independent
Classifier: Programming Language :: JavaScript
Classifier: Programming Language :: Python :: 3 :: Only
Classifier: Programming Language :: Python :: 3.7
Classifier: Programming Language :: Python :: 3.8
Classifier: Programming Language :: Python :: 3.9
Classifier: Programming Language :: Python :: 3.10
Classifier: Typing :: Typed
Classifier: Development Status :: 4 - Beta
Classifier: License :: OSI Approved
Requires-Python: ~=3.7
License-File: LICENSE
Requires-Dist: aws-cdk-lib (<3.0.0,>=2.10.0)
Requires-Dist: constructs (<11.0.0,>=10.0.5)
Requires-Dist: jsii (<2.0.0,>=1.75.0)
Requires-Dist: publication (>=0.0.3)
Requires-Dist: typeguard (~=2.13.3)
